pycaged/__init__.py
pycaged-2.0.dist-info/LICENSE
pycaged-2.0.dist-info/METADATA
pycaged-2.0.dist-info/WHEEL
pycaged-2.0.dist-info/top_level.txt
pycaged-2.0.dist-info/RECORD
