Metadata-Version: 2.1
Name: pycaged
Version: 2.0
Summary: fetches CAGED microdata / busca microdados do CAGED
Home-page: UNKNOWN
Author: Heitor Caixeta
Author-email: heitor.ca.mesquita@gmail.com
License: MIT
Keywords: caged,ibge,emprego
Platform: UNKNOWN
Classifier: Operating System :: Microsoft :: Windows :: Windows 10
Classifier: License :: OSI Approved :: MIT License
Classifier: Programming Language :: Python :: 3.8
License-File: LICENSE
Requires-Dist: py7zr
Requires-Dist: pandas
Requires-Dist: wget
